pygnip.py
pygnip/pygnip.py
pygnip/__init__.py
gnip/gnip.py
gnip/__init__.py
pygnip-1.0.1.a1.dist-info/DESCRIPTION.rst
pygnip-1.0.1.a1.dist-info/WHEEL
pygnip-1.0.1.a1.dist-info/RECORD
pygnip-1.0.1.a1.dist-info/METADATA
pygnip-1.0.1.a1.dist-info/top_level.txt
pygnip-1.0.1.a1.dist-info/metadata.json
