Metadata-Version: 2.0
Name: pygnip
Version: 1.0.1.a1
Summary: A wrapper for the Gnip API
Home-page: https://github.com/benjiao/python-gnip
Author: Benjie Jiao
Author-email: benjiao12@gmail.com
License: BSD
Keywords: gnip api powertrack
Platform: any
Classifier: Environment :: Web Environment
Classifier: Intended Audience :: Developers
Classifier: License :: OSI Approved :: BSD License
Classifier: Operating System :: OS Independent
Classifier: Programming Language :: Python
Classifier: Topic :: Internet :: WWW/HTTP :: Dynamic Content
Classifier: Topic :: Software Development :: Libraries :: Python Modules
